{
  "db_name": "PostgreSQL",
  "query": "\n        select schemaname as \"schemaname!\", tablename as \"tablename!\"\n        from pg_tables\n        where schemaname in ('public', 'tower_sessions')\n        and tablename != '_sqlx_migrations';",
  "describe": {
    "columns": [
      {
        "ordinal": 0,
        "name": "schemaname!",
        "type_info": "Name"
      },
      {
        "ordinal": 1,
        "name": "tablename!",
        "type_info": "Name"
      }
    ],
    "parameters": {
      "Left": []
    },
    "nullable": [
      true,
      true
    ]
  },
  "hash": "d5307b3bd3ea83469276ae2242eff9b485c6db8cf387444366333e5f4b3ce7be"
}
